bk_resource/__init__.py
bk_resource/apps.py
bk_resource/base.py
bk_resource/exceptions.py
bk_resource/routers.py
bk_resource/serializers.py
bk_resource/settings.py
bk_resource/tasks.py
bk_resource/tools.py
bk_resource/viewsets.py
bk_resource/conf/__init__.py
bk_resource/conf/app_template/__init__.py-tpl
bk_resource/conf/app_template/admin.py-tpl
bk_resource/conf/app_template/apps.py-tpl
bk_resource/conf/app_template/models.py-tpl
bk_resource/conf/app_template/resources.py-tpl
bk_resource/conf/app_template/serializers.py-tpl
bk_resource/conf/app_template/urls.py-tpl
bk_resource/conf/app_template/views.py-tpl
bk_resource/conf/app_template/migrations/__init__.py-tpl
bk_resource/contrib/__init__.py
bk_resource/contrib/api.py
bk_resource/contrib/bk_api.py
bk_resource/contrib/cache.py
bk_resource/contrib/model.py
bk_resource/locale/en/LC_MESSAGES/django.mo
bk_resource/locale/en/LC_MESSAGES/django.po
bk_resource/locale/zh_CN/LC_MESSAGES/django.mo
bk_resource/locale/zh_CN/LC_MESSAGES/django.po
bk_resource/management/__init__.py
bk_resource/management/exceptions.py
bk_resource/management/finder.py
bk_resource/management/root.py
bk_resource/management/stub_file_generator.py
bk_resource/management/commands/__init__.py
bk_resource/management/commands/generate_resource_stub_file.py
bk_resource/management/commands/start_resource.py
bk_resource/utils/__init__.py
bk_resource/utils/cache.py
bk_resource/utils/common_utils.py
bk_resource/utils/factory.py
bk_resource/utils/generators.py
bk_resource/utils/inspectors.py
bk_resource/utils/local.py
bk_resource/utils/logger.py
bk_resource/utils/request.py
bk_resource/utils/request_log.py
bk_resource/utils/text.py
bk_resource/utils/thread_backend.py
bk_resource/utils/time_tools.py
bk_resource-0.4.14.dist-info/licenses/LICENSE.txt
bk_resource-0.4.14.dist-info/METADATA
bk_resource-0.4.14.dist-info/WHEEL
bk_resource-0.4.14.dist-info/top_level.txt
bk_resource-0.4.14.dist-info/RECORD
