Metadata-Version: 2.4
Name: bk_resource
Version: 0.4.14
Summary: Bk Resource
Home-page: https://bk.tencent.com
Author: blueking
Author-email: blueking@tencent.com
License-File: LICENSE.txt
Requires-Dist: blueapps>=4.12.0
Requires-Dist: django>=3.2.18
Requires-Dist: djangorestframework>=3.12.0
Requires-Dist: drf-yasg>=1.20.0
Requires-Dist: pyinstrument>=3.4.2
Requires-Dist: arrow>=1.2.0
Requires-Dist: django-rest-framework-condition>=0.1.1
Requires-Dist: celery>=4.4.0
Dynamic: author
Dynamic: author-email
Dynamic: description
Dynamic: description-content-type
Dynamic: home-page
Dynamic: license-file
Dynamic: requires-dist
Dynamic: summary
